wallapop_auto_adjust/__init__.py
wallapop_auto_adjust/api_analyzer.py
wallapop_auto_adjust/cli.py
wallapop_auto_adjust/config.py
wallapop_auto_adjust/cookie_extraction_guide.py
wallapop_auto_adjust/price_adjuster.py
wallapop_auto_adjust/session_manager.py
wallapop_auto_adjust/session_persistence.py
wallapop_auto_adjust/wallapop_client.py
wallapop_auto_adjust-2.2.0.dist-info/METADATA
wallapop_auto_adjust-2.2.0.dist-info/WHEEL
wallapop_auto_adjust-2.2.0.dist-info/entry_points.txt
wallapop_auto_adjust-2.2.0.dist-info/licenses/LICENSE
wallapop_auto_adjust-2.2.0.dist-info/RECORD
