Metadata-Version: 2.4
Name: wallapop-auto-adjust
Version: 2.2.0
Summary: Automatic price adjustment tool for Wallapop sales
License: MIT
License-File: LICENSE
Keywords: wallapop,automation,pricing,cli,marketplace
Author: Alexander Serov
Author-email: asserov@gmail.com
Requires-Python: >=3.10,<4.0
Classifier: Development Status :: 4 - Beta
Classifier: Intended Audience :: End Users/Desktop
Classifier: License :: OSI Approved :: MIT License
Classifier: Programming Language :: Python
Classifier: Programming Language :: Python :: 3
Classifier: Programming Language :: Python :: 3.10
Classifier: Programming Language :: Python :: 3.11
Classifier: Programming Language :: Python :: 3.12
Classifier: Environment :: Console
Classifier: Operating System :: OS Independent
Classifier: Topic :: Internet
Classifier: Topic :: Utilities
Requires-Dist: beautifulsoup4 (>=4.13.4,<5.0.0)
Requires-Dist: python-dateutil (>=2.9.0.post0,<3.0.0)
Requires-Dist: python-dotenv (>=1.1.1,<2.0.0)
Requires-Dist: requests (>=2.32.4,<3.0.0)
Requires-Dist: selenium (>=4.35.0,<5.0.0)
Requires-Dist: undetected-chromedriver (>=3.5.5,<4.0.0)
Project-URL: Homepage, https://github.com/Alexander-Serov/wallapop-auto-adjust
Project-URL: Issues, https://github.com/Alexander-Serov/wallapop-auto-adjust/issues
Project-URL: Repository, https://github.com/Alexander-Serov/wallapop-auto-adjust
